tweetipy/__init__.py
tweetipy/enums/expansions/__init__.py
tweetipy/enums/expansions/Tweet.py
tweetipy/enums/fields/__init__.py
tweetipy/enums/fields/_media/__init__.py
tweetipy/enums/fields/_media/main.py
tweetipy/enums/fields/_place/__init__.py
tweetipy/enums/fields/_place/main.py
tweetipy/enums/fields/_poll/__init__.py
tweetipy/enums/fields/_poll/main.py
tweetipy/enums/fields/_tweet/__init__.py
tweetipy/enums/fields/_tweet/main.py
tweetipy/enums/fields/_user/__init__.py
tweetipy/enums/fields/_user/main.py
tweetipy/handlers/__init__.py
tweetipy/handlers/Media.py
tweetipy/handlers/Tweets.py
tweetipy/helpers/__init__.py
tweetipy/helpers/API.py
tweetipy/helpers/QueryBuilder/__init__.py
tweetipy/helpers/QueryBuilder/alt.py
tweetipy/helpers/QueryBuilder/lang.py
tweetipy/helpers/QueryBuilder/main.py
tweetipy/main.py
tweetipy/types/__init__.py
tweetipy/types/_attachments/__init__.py
tweetipy/types/_attachments/_main.py
tweetipy/types/_geo.py
tweetipy/types/_includes/__init__.py
tweetipy/types/_includes/_main.py
tweetipy/types/_media_to_upload.py
tweetipy/types/_place/__init__.py
tweetipy/types/_place/_main.py
tweetipy/types/_scope/__init__.py
tweetipy/types/_scope/_main.py
tweetipy/types/context_annotation/__init__.py
tweetipy/types/context_annotation/_domain.py
tweetipy/types/context_annotation/_entity.py
tweetipy/types/context_annotation/_main.py
tweetipy/types/media/__init__.py
tweetipy/types/media/_main.py
tweetipy/types/media/_variant.py
tweetipy/types/media/metrics/__init__.py
tweetipy/types/media/metrics/_nonpublic.py
tweetipy/types/media/metrics/_organic.py
tweetipy/types/media/metrics/_promoted.py
tweetipy/types/media/metrics/_public.py
tweetipy/types/poll/__init__.py
tweetipy/types/poll/_main.py
tweetipy/types/poll/_option.py
tweetipy/types/tweet/__init__.py
tweetipy/types/tweet/_main.py
tweetipy/types/tweet/_reply_config.py
tweetipy/types/tweet/metrics/__init__.py
tweetipy/types/tweet/metrics/_public.py
tweetipy/types/user/__init__.py
tweetipy-0.1.10.dist-info/LICENSE
tweetipy-0.1.10.dist-info/WHEEL
tweetipy-0.1.10.dist-info/METADATA
tweetipy-0.1.10.dist-info/RECORD
