Metadata-Version: 2.1
Name: tweetipy
Version: 0.1.10
Summary: A simple "type hinted" Python client for interacting with Twitter's API.
Home-page: https://github.com/omirete/tweetipy
License: MIT
Author: Federico Giancarelli
Author-email: hello@federicogiancarelli.com
Requires-Python: >=3.9,<4.0
Classifier: License :: OSI Approved :: MIT License
Classifier: Programming Language :: Python :: 3
Classifier: Programming Language :: Python :: 3.9
Classifier: Programming Language :: Python :: 3.10
Requires-Dist: requests (>=2.28.1,<3.0.0)
Requires-Dist: requests-oauthlib (>=1.3.1,<2.0.0)
Requires-Dist: segno (>=1.5.2,<2.0.0)
Project-URL: Repository, https://github.com/omirete/tweetipy
